coinbase/__init__.py
coinbase/__version__.py
coinbase/constants.py
coinbase/jwt_generator.py
coinbase/rest/__init__.py
coinbase/rest/accounts.py
coinbase/rest/common.py
coinbase/rest/convert.py
coinbase/rest/fees.py
coinbase/rest/futures.py
coinbase/rest/market_data.py
coinbase/rest/orders.py
coinbase/rest/portfolios.py
coinbase/rest/products.py
coinbase/rest/rest_base.py
tests/__init__.py
tests/constants.py
tests/test_jwt_generator.py
tests/rest/__init__.py
tests/rest/test_accounts.py
tests/rest/test_common.py
tests/rest/test_convert.py
tests/rest/test_fees.py
tests/rest/test_market_data.py
tests/rest/test_orders.py
tests/rest/test_portfolios.py
tests/rest/test_products.py
tests/rest/test_rest_base.py
uri_test_pypi_project-1.0.0.dist-info/LICENSE.md
uri_test_pypi_project-1.0.0.dist-info/METADATA
uri_test_pypi_project-1.0.0.dist-info/WHEEL
uri_test_pypi_project-1.0.0.dist-info/top_level.txt
uri_test_pypi_project-1.0.0.dist-info/RECORD
