Metadata-Version: 2.1
Name: uri-test-pypi-project
Version: 1.0.0
Summary: Uri Test PyPi Project
Home-page: UNKNOWN
Author: Uri
License: Apache 2.0
Platform: UNKNOWN
Requires-Python: >=3.8
Requires-Dist: requests ==2.31.0
Requires-Dist: black ==23.3.0
Requires-Dist: isort ==5.12.0
Requires-Dist: cryptography ==41.0.6
Requires-Dist: PyJWT ==2.8.0
Provides-Extra: test
Requires-Dist: requests-mock ==1.11.0 ; extra == 'test'
